response_shaper/__init__.py
response_shaper/apps.py
response_shaper/decorators.py
response_shaper/exceptions.py
response_shaper/middleware.py
response_shaper/responses.py
response_shaper/settings/__init__.py
response_shaper/settings/check.py
response_shaper/settings/conf.py
response_shaper/tests/__init__.py
response_shaper/tests/conftest.py
response_shaper/tests/constants.py
response_shaper/tests/setup.py
response_shaper/tests/test_api_responses.py
response_shaper/tests/test_decorators.py
response_shaper/tests/test_exceptions.py
response_shaper/tests/test_middleware.py
response_shaper/tests/test_settings.py
response_shaper/types.py
response_shaper/validators/__init__.py
response_shaper/validators/config_validators.py
api_response_shaper-1.2.1.dist-info/AUTHORS.md
api_response_shaper-1.2.1.dist-info/LICENSE
api_response_shaper-1.2.1.dist-info/METADATA
api_response_shaper-1.2.1.dist-info/WHEEL
api_response_shaper-1.2.1.dist-info/RECORD
